supportsx/__init__.py
supportsx/_supports.py
supportsx/py.typed
supportsx/u/__init__.py
supportsx/u/_unions.py
supportsx-0.0.3.dist-info/licenses/LICENSE
supportsx-0.0.3.dist-info/METADATA
supportsx-0.0.3.dist-info/WHEEL
supportsx-0.0.3.dist-info/top_level.txt
supportsx-0.0.3.dist-info/RECORD
