Metadata-Version: 2.4
Name: supportsx
Version: 0.0.3
Summary: A Python library that supplies runtime-checkable, fully parameterized, and well-documented protocols for nearly all dunder methods/attributes.
Author-email: Tanner Corcoran <tannerbcorcoran@gmail.com>
Maintainer-email: Tanner Corcoran <tannerbcorcoran@gmail.com>
License: Apache License
Project-URL: Homepage, https://github.com/tanrbobanr/supportsx
Project-URL: Documentation, https://github.com/tanrbobanr/supportsx/blob/main/README.md
Project-URL: Changelog, https://github.com/tanrbobanr/supportsx/blob/main/CHANGELOG.md
Project-URL: Source, https://github.com/tanrbobanr/supportsx
Project-URL: Issues, https://github.com/tanrbobanr/supportsx/issues
Keywords: supports,protocols
Classifier: Development Status :: 3 - Alpha
Classifier: Operating System :: OS Independent
Classifier: Programming Language :: Python
Classifier: Programming Language :: Python :: 3
Classifier: Programming Language :: Python :: 3 :: Only
Classifier: Programming Language :: Python :: 3.9
Classifier: Programming Language :: Python :: 3.10
Classifier: Programming Language :: Python :: 3.11
Classifier: Programming Language :: Python :: 3.12
Classifier: Programming Language :: Python :: 3.13
Classifier: Programming Language :: Python :: 3.14
Classifier: Topic :: Software Development
Classifier: Topic :: Software Development :: Libraries
Classifier: Typing :: Typed
Classifier: Topic :: Utilities
Classifier: Intended Audience :: Developers
Classifier: License :: OSI Approved :: Apache Software License
Requires-Python: >=3.9
License-File: LICENSE
Requires-Dist: typing_extensions>=4.4.0; python_version < "3.10"
Dynamic: license-file
